llama_index/packs/self_discover/__init__.py
llama_index/packs/self_discover/base.py
llama_index_packs_self_discover-0.4.1.dist-info/METADATA
llama_index_packs_self_discover-0.4.1.dist-info/WHEEL
llama_index_packs_self_discover-0.4.1.dist-info/licenses/LICENSE
llama_index_packs_self_discover-0.4.1.dist-info/RECORD
