Metadata-Version: 2.4
Name: llama-index-packs-self-discover
Version: 0.4.1
Summary: llama-index packs self_discover paper implementation
Author-email: Ravi Theja <ravi03071991@gmail.com>
License-Expression: MIT
License-File: LICENSE
Keywords: discover,self,self-discover,task
Requires-Python: <4.0,>=3.9
Requires-Dist: llama-index-core<0.15,>=0.13.0
Requires-Dist: llama-index-llms-openai<0.6,>=0.5.0
